Metadata-Version: 1.0
Name: pyprackiller
Version: 0.1
Summary: The Goal Of This Library Is To Help Students To Learn Python
Home-page: UNKNOWN
Author: UNKNOWN
Author-email: UNKNOWN
License: UNKNOWN
Platform: UNKNOWN
